DD&CO LAB/Icarus Verilog/SR_flipflop.v
module SR_flipflop(
    input S,
    input R,
    input CLK,
    output reg Q,
    output Q_bar
);

always @(posedge CLK)
begin
    if (S && !R)
        Q <= 1;
    else if (!S && R)
        Q <= 0;
    else if (S && R)
        Q <= 1'bx; // undefined state
    // if both S and R are 0, Q remains unchanged
end

assign Q_bar = ~Q;

endmodule

DD&CO LAB/Icarus Verilog/tb_SR_flipflop.v
module tb_SR_flipflop;
    reg S, R, CLK;
    wire Q, Q_bar;

    // Instantiate the SR flip-flop
    SR_flipflop uut (
        .S(S),
        .R(R),
        .CLK(CLK),
        .Q(Q),
        .Q_bar(Q_bar)
    );

    // Clock generation
    always #5 CLK = ~CLK;

    initial begin
        // Initialize inputs
        S = 0; R = 0; CLK = 0;

        // Apply test vectors
        #10 S = 1; R = 0; // Set
        #10 S = 0; R = 1; // Reset
        #10 S = 1; R = 1; // Undefined state
        #10 S = 0; R = 0; // No change

        // End simulation
        #10 $finish;
    end

    initial begin
        // Monitor signals
        $monitor("Time=%0t | S=%b | R=%b | CLK=%b | Q=%b | Q_bar=%b", $time, S, R, CLK, Q, Q_bar);
    end

    // Generate VCD file
    initial begin
        $dumpfile("sr_flipflop.vcd");
        $dumpvars(0, tb_SR_flipflop);
    end
endmodule

DD&CO LAB/Icarus Verilog/sr_flipflop.vcd
$date
	Sun Dec 08 00:29:54 2024
$end
$version
	Icarus Verilog
$end
$timescale
	1s
$end
$scope module tb_SR_flipflop $end
$var wire 1 ! Q_bar $end
$var wire 1 " Q $end
$var reg 1 # CLK $end
$var reg 1 $ R $end
$var reg 1 % S $end
$scope module uut $end
$var wire 1 # CLK $end
$var wire 1 ! Q_bar $end
$var wire 1 $ R $end
$var wire 1 % S $end
$var reg 1 " Q $end
$upscope $end
$upscope $end
$enddefinitions $end
$comment Show the parameter values. $end
$dumpall
$end
#0
$dumpvars
0%
0$
0#
x"
x!
$end
#5
1#
#10
0#
1%
#15
0!
1"
1#
#20
0#
1$
0%
#25
1!
0"
1#
#30
0#
1%
#35
x!
x"
1#
#40
0#
0$
0%
